{
"meta":{"test_sets":[],"test_metrics":[],"learn_metrics":[{"best_value":"Min","name":"Logloss"}],"launch_mode":"Train","parameters":"","iteration_count":100,"learn_sets":["learn"],"name":"experiment"},
"iterations":[
{"learn":[0.5347104419],"iteration":0,"passed_time":0.09019495538,"remaining_time":8.929300582},
{"learn":[0.4842150933],"iteration":1,"passed_time":0.1133932658,"remaining_time":5.556270026},
{"learn":[0.4643151223],"iteration":2,"passed_time":0.1377305804,"remaining_time":4.453288765},
{"learn":[0.4563512471],"iteration":3,"passed_time":0.160742439,"remaining_time":3.857818537},
{"learn":[0.4532467558],"iteration":4,"passed_time":0.1830833201,"remaining_time":3.478583081},
{"learn":[0.4516119486],"iteration":5,"passed_time":0.2089962901,"remaining_time":3.274275212},
{"learn":[0.4508822967],"iteration":6,"passed_time":0.2316432029,"remaining_time":3.077545411},
{"learn":[0.4503332484],"iteration":7,"passed_time":0.2545770222,"remaining_time":2.927635755},
{"learn":[0.4499434529],"iteration":8,"passed_time":0.2769917338,"remaining_time":2.800694197},
{"learn":[0.4496657554],"iteration":9,"passed_time":0.2999088036,"remaining_time":2.699179232},
{"learn":[0.4495729157],"iteration":10,"passed_time":0.322178146,"remaining_time":2.60671409},
{"learn":[0.4494204666],"iteration":11,"passed_time":0.3453174174,"remaining_time":2.532327728},
{"learn":[0.4492858739],"iteration":12,"passed_time":0.3683386088,"remaining_time":2.465035305},
{"learn":[0.4491894075],"iteration":13,"passed_time":0.3936831818,"remaining_time":2.418339545},
{"learn":[0.449099667],"iteration":14,"passed_time":0.4183373608,"remaining_time":2.370578378},
{"learn":[0.4489723379],"iteration":15,"passed_time":0.4430602874,"remaining_time":2.326066509},
{"learn":[0.448860893],"iteration":16,"passed_time":0.4642516237,"remaining_time":2.266640281},
{"learn":[0.4487925927],"iteration":17,"passed_time":0.486554965,"remaining_time":2.216528174},
{"learn":[0.4487174191],"iteration":18,"passed_time":0.5088875543,"remaining_time":2.169467995},
{"learn":[0.4486328516],"iteration":19,"passed_time":0.5318664971,"remaining_time":2.127465988},
{"learn":[0.4485717689],"iteration":20,"passed_time":0.5587166449,"remaining_time":2.101838807},
{"learn":[0.4484948119],"iteration":21,"passed_time":0.5828895479,"remaining_time":2.066608397},
{"learn":[0.4484231073],"iteration":22,"passed_time":0.6042115459,"remaining_time":2.022795175},
{"learn":[0.4483674298],"iteration":23,"passed_time":0.6254094649,"remaining_time":1.980463306},
{"learn":[0.4483026141],"iteration":24,"passed_time":0.6466414249,"remaining_time":1.939924275},
{"learn":[0.4482189578],"iteration":25,"passed_time":0.6680220459,"remaining_time":1.901293515},
{"learn":[0.44809675],"iteration":26,"passed_time":0.6912512313,"remaining_time":1.868938514},
{"learn":[0.4480339698],"iteration":27,"passed_time":0.7138173968,"remaining_time":1.835530449},
{"learn":[0.4479481677],"iteration":28,"passed_time":0.7347250756,"remaining_time":1.798809668},
{"learn":[0.4479028854],"iteration":29,"passed_time":0.7556048383,"remaining_time":1.763077956},
{"learn":[0.4478184652],"iteration":30,"passed_time":0.779876321,"remaining_time":1.735853747},
{"learn":[0.4477218528],"iteration":31,"passed_time":0.8043901296,"remaining_time":1.709329025},
{"learn":[0.447650939],"iteration":32,"passed_time":0.8254914689,"remaining_time":1.675997831},
{"learn":[0.4476094004],"iteration":33,"passed_time":0.8497081215,"remaining_time":1.649433412},
{"learn":[0.4475481683],"iteration":34,"passed_time":0.8720450026,"remaining_time":1.619512148},
{"learn":[0.4474541015],"iteration":35,"passed_time":0.8974660311,"remaining_time":1.595495166},
{"learn":[0.4474031923],"iteration":36,"passed_time":0.9223567852,"remaining_time":1.570499391},
{"learn":[0.4473655992],"iteration":37,"passed_time":0.9448909517,"remaining_time":1.541664184},
{"learn":[0.4473212316],"iteration":38,"passed_time":0.9712276577,"remaining_time":1.51909967},
{"learn":[0.4472649742],"iteration":39,"passed_time":0.9978925197,"remaining_time":1.49683878},
{"learn":[0.4472226232],"iteration":40,"passed_time":1.023047973,"remaining_time":1.472190986},
{"learn":[0.447068512],"iteration":41,"passed_time":1.050666136,"remaining_time":1.450919902},
{"learn":[0.4470267236],"iteration":42,"passed_time":1.073125346,"remaining_time":1.422514994},
{"learn":[0.4469829964],"iteration":43,"passed_time":1.100380189,"remaining_time":1.400483877},
{"learn":[0.4469388142],"iteration":44,"passed_time":1.123672413,"remaining_time":1.373377394},
{"learn":[0.4468869616],"iteration":45,"passed_time":1.147963562,"remaining_time":1.347609399},
{"learn":[0.4468399389],"iteration":46,"passed_time":1.174401557,"remaining_time":1.32432516},
{"learn":[0.4467900235],"iteration":47,"passed_time":1.201666524,"remaining_time":1.301805401},
{"learn":[0.4467195598],"iteration":48,"passed_time":1.239595761,"remaining_time":1.290191506},
{"learn":[0.4466734291],"iteration":49,"passed_time":1.298420802,"remaining_time":1.298420802},
{"learn":[0.4466472616],"iteration":50,"passed_time":1.320831055,"remaining_time":1.269033759},
{"learn":[0.4466065102],"iteration":51,"passed_time":1.346115505,"remaining_time":1.242568159},
{"learn":[0.4465522027],"iteration":52,"passed_time":1.371015259,"remaining_time":1.215805985},
{"learn":[0.4464934635],"iteration":53,"passed_time":1.396235377,"remaining_time":1.189385692},
{"learn":[0.4464289044],"iteration":54,"passed_time":1.422752827,"remaining_time":1.164070495},
{"learn":[0.4464050988],"iteration":55,"passed_time":1.444281485,"remaining_time":1.134792596},
{"learn":[0.4463365016],"iteration":56,"passed_time":1.468642174,"remaining_time":1.107923044},
{"learn":[0.4463009378],"iteration":57,"passed_time":1.495129459,"remaining_time":1.082679953},
{"learn":[0.4462541711],"iteration":58,"passed_time":1.521383502,"remaining_time":1.057232603},
{"learn":[0.4462214725],"iteration":59,"passed_time":1.54490926,"remaining_time":1.029939507},
{"learn":[0.44619659],"iteration":60,"passed_time":1.569994259,"remaining_time":1.003766821},
{"learn":[0.4461084725],"iteration":61,"passed_time":1.597785625,"remaining_time":0.979287964},
{"learn":[0.44605938],"iteration":62,"passed_time":1.622324433,"remaining_time":0.9527937147},
{"learn":[0.4460258826],"iteration":63,"passed_time":1.645806193,"remaining_time":0.9257659837},
{"learn":[0.4459660744],"iteration":64,"passed_time":1.66999568,"remaining_time":0.8992284429},
{"learn":[0.4459351187],"iteration":65,"passed_time":1.696729872,"remaining_time":0.8740729646},
{"learn":[0.4458667295],"iteration":66,"passed_time":1.725953774,"remaining_time":0.8500966351},
{"learn":[0.4458372804],"iteration":67,"passed_time":1.753891635,"remaining_time":0.8253607693},
{"learn":[0.4457963382],"iteration":68,"passed_time":1.779607403,"remaining_time":0.799533761},
{"learn":[0.4457519566],"iteration":69,"passed_time":1.806644003,"remaining_time":0.7742760013},
{"learn":[0.4457171782],"iteration":70,"passed_time":1.831328347,"remaining_time":0.748007353},
{"learn":[0.4456673333],"iteration":71,"passed_time":1.855413378,"remaining_time":0.721549647},
{"learn":[0.4456257163],"iteration":72,"passed_time":1.881089232,"remaining_time":0.6957453324},
{"learn":[0.4455945962],"iteration":73,"passed_time":1.902339066,"remaining_time":0.6683894017},
{"learn":[0.4455451016],"iteration":74,"passed_time":1.924295919,"remaining_time":0.641431973},
{"learn":[0.4455068246],"iteration":75,"passed_time":1.947895008,"remaining_time":0.6151247394},
{"learn":[0.445483469],"iteration":76,"passed_time":1.970453798,"remaining_time":0.5885771085},
{"learn":[0.4454618557],"iteration":77,"passed_time":1.994828944,"remaining_time":0.5626440612},
{"learn":[0.4454372837],"iteration":78,"passed_time":2.01884452,"remaining_time":0.5366548723},
{"learn":[0.4453973633],"iteration":79,"passed_time":2.046675176,"remaining_time":0.5116687939},
{"learn":[0.4453618324],"iteration":80,"passed_time":2.073545823,"remaining_time":0.4863872918},
{"learn":[0.4453288511],"iteration":81,"passed_time":2.099324964,"remaining_time":0.4608274312},
{"learn":[0.4452727333],"iteration":82,"passed_time":2.12675926,"remaining_time":0.4356012942},
{"learn":[0.4452264466],"iteration":83,"passed_time":2.150781877,"remaining_time":0.4096727384},
{"learn":[0.4451937949],"iteration":84,"passed_time":2.174016436,"remaining_time":0.3836499593},
{"learn":[0.4451632833],"iteration":85,"passed_time":2.197753896,"remaining_time":0.35777389},
{"learn":[0.4451326526],"iteration":86,"passed_time":2.223808403,"remaining_time":0.3322932096},
{"learn":[0.4450976788],"iteration":87,"passed_time":2.248137052,"remaining_time":0.3065641434},
{"learn":[0.4450563826],"iteration":88,"passed_time":2.277487449,"remaining_time":0.2814872128},
{"learn":[0.4450142999],"iteration":89,"passed_time":2.306045998,"remaining_time":0.2562273331},
{"learn":[0.4449830875],"iteration":90,"passed_time":2.330979709,"remaining_time":0.2305364547},
{"learn":[0.4449541176],"iteration":91,"passed_time":2.358496168,"remaining_time":0.2050866233},
{"learn":[0.4449122428],"iteration":92,"passed_time":2.382085049,"remaining_time":0.1792967241},
{"learn":[0.4448854779],"iteration":93,"passed_time":2.406791726,"remaining_time":0.1536250038},
{"learn":[0.4448574122],"iteration":94,"passed_time":2.431922014,"remaining_time":0.1279958955},
{"learn":[0.444835021],"iteration":95,"passed_time":2.457313836,"remaining_time":0.1023880765},
{"learn":[0.4447937292],"iteration":96,"passed_time":2.483088603,"remaining_time":0.07679655472},
{"learn":[0.444767155],"iteration":97,"passed_time":2.507514498,"remaining_time":0.05117376527},
{"learn":[0.4447435131],"iteration":98,"passed_time":2.531142752,"remaining_time":0.02556709851},
{"learn":[0.4447253413],"iteration":99,"passed_time":2.555644311,"remaining_time":0}
]}